[
	{
		"inputs": [],
		"name": "getBatchSize",
		"outputs": [
			{
				"internalType": "int256",
				"name": "",
				"type": "int256"
			}
		],
		"stateMutability": "nonpayable",
		"type": "function"
	},
	{
		"inputs": [],
		"name": "getLearningRate",
		"outputs": [
			{
				"internalType": "int256",
				"name": "",
				"type": "int256"
			}
		],
		"stateMutability": "nonpayable",
		"type": "function"
	},
	{
		"inputs": [],
		"name": "getPrecision",
		"outputs": [
			{
				"internalType": "int256",
				"name": "",
				"type": "int256"
			}
		],
		"stateMutability": "nonpayable",
		"type": "function"
	},
	{
		"inputs": [],
		"name": "getRigesterCheck",
		"outputs": [
			{
				"internalType": "bool",
				"name": "",
				"type": "bool"
			}
		],
		"stateMutability": "nonpayable",
		"type": "function"
	},
	{
		"inputs": [],
		"name": "getRoundNumber",
		"outputs": [
			{
				"internalType": "uint256",
				"name": "",
				"type": "uint256"
			}
		],
		"stateMutability": "nonpayable",
		"type": "function"
	},
	{
		"inputs": [],
		"name": "initNewRound",
		"outputs": [],
		"stateMutability": "nonpayable",
		"type": "function"
	},
	{
		"inputs": [],
		"name": "register",
		"outputs": [],
		"stateMutability": "nonpayable",
		"type": "function"
	},
	{
		"inputs": [
			{
				"internalType": "address",
				"name": "client",
				"type": "address"
			}
		],
		"name": "roundUpdateOutstanding",
		"outputs": [
			{
				"internalType": "bool",
				"name": "",
				"type": "bool"
			}
		],
		"stateMutability": "nonpayable",
		"type": "function"
	},
	{
		"inputs": [
			{
				"internalType": "string",
				"name": "modelHash",
				"type": "string"
			},
			{
				"internalType": "bytes32",
				"name": "fact",
				"type": "bytes32"
			}
		],
		"name": "update_with_proof",
		"outputs": [
			{
				"internalType": "bool",
				"name": "",
				"type": "bool"
			}
		],
		"stateMutability": "nonpayable",
		"type": "function"
	},
	{
		"inputs": [
			{
				"internalType": "string",
				"name": "modelHash",
				"type": "string"
			}
		],
		"name": "update_without_proof",
		"outputs": [
			{
				"internalType": "bool",
				"name": "",
				"type": "bool"
			}
		],
		"stateMutability": "nonpayable",
		"type": "function"
	},
	{
		"inputs": [
			{
				"internalType": "uint256",
				"name": "inputDim",
				"type": "uint256"
			},
			{
				"internalType": "uint256",
				"name": "outputDim",
				"type": "uint256"
			},
			{
				"internalType": "uint256",
				"name": "participantsCount",
				"type": "uint256"
			},
			{
				"internalType": "int256",
				"name": "_precision",
				"type": "int256"
			},
			{
				"internalType": "int256",
				"name": "learningRate",
				"type": "int256"
			},
			{
				"internalType": "int256",
				"name": "_batchSize",
				"type": "int256"
			},
			{
				"internalType": "uint256",
				"name": "_numRound",
				"type": "uint256"
			},
			{
				"internalType": "uint256",
				"name": "updateInterval",
				"type": "uint256"
			}
		],
		"stateMutability": "nonpayable",
		"type": "constructor"
	},
	{
		"inputs": [],
		"name": "check",
		"outputs": [
			{
				"internalType": "uint256",
				"name": "",
				"type": "uint256"
			}
		],
		"stateMutability": "view",
		"type": "function"
	},
	{
		"inputs": [
			{
				"internalType": "address",
				"name": "",
				"type": "address"
			}
		],
		"name": "clients",
		"outputs": [
			{
				"internalType": "uint256",
				"name": "",
				"type": "uint256"
			}
		],
		"stateMutability": "view",
		"type": "function"
	},
	{
		"inputs": [
			{
				"internalType": "uint256",
				"name": "",
				"type": "uint256"
			}
		],
		"name": "clientsModelsHash",
		"outputs": [
			{
				"internalType": "string",
				"name": "",
				"type": "string"
			}
		],
		"stateMutability": "view",
		"type": "function"
	},
	{
		"inputs": [],
		"name": "getModelHAsh",
		"outputs": [
			{
				"internalType": "string[]",
				"name": "",
				"type": "string[]"
			}
		],
		"stateMutability": "view",
		"type": "function"
	},
	{
		"inputs": [],
		"name": "inputDimension",
		"outputs": [
			{
				"internalType": "uint256",
				"name": "",
				"type": "uint256"
			}
		],
		"stateMutability": "view",
		"type": "function"
	},
	{
		"inputs": [],
		"name": "learning_rate",
		"outputs": [
			{
				"internalType": "int256",
				"name": "",
				"type": "int256"
			}
		],
		"stateMutability": "view",
		"type": "function"
	},
	{
		"inputs": [],
		"name": "numClientsRegistered",
		"outputs": [
			{
				"internalType": "uint256",
				"name": "",
				"type": "uint256"
			}
		],
		"stateMutability": "view",
		"type": "function"
	},
	{
		"inputs": [],
		"name": "numParticipants",
		"outputs": [
			{
				"internalType": "uint256",
				"name": "",
				"type": "uint256"
			}
		],
		"stateMutability": "view",
		"type": "function"
	},
	{
		"inputs": [],
		"name": "outputDimension",
		"outputs": [
			{
				"internalType": "uint256",
				"name": "",
				"type": "uint256"
			}
		],
		"stateMutability": "view",
		"type": "function"
	},
	{
		"inputs": [],
		"name": "Precision",
		"outputs": [
			{
				"internalType": "int256",
				"name": "",
				"type": "int256"
			}
		],
		"stateMutability": "view",
		"type": "function"
	},
	{
		"inputs": [],
		"name": "prevRoundUpdateCount",
		"outputs": [
			{
				"internalType": "uint256",
				"name": "",
				"type": "uint256"
			}
		],
		"stateMutability": "view",
		"type": "function"
	},
	{
		"inputs": [
			{
				"internalType": "address",
				"name": "",
				"type": "address"
			}
		],
		"name": "receivedFacts",
		"outputs": [
			{
				"internalType": "bytes32",
				"name": "",
				"type": "bytes32"
			}
		],
		"stateMutability": "view",
		"type": "function"
	},
	{
		"inputs": [],
		"name": "registerCheck",
		"outputs": [
			{
				"internalType": "bool",
				"name": "",
				"type": "bool"
			}
		],
		"stateMutability": "view",
		"type": "function"
	},
	{
		"inputs": [
			{
				"internalType": "address",
				"name": "",
				"type": "address"
			}
		],
		"name": "registeredAddressList",
		"outputs": [
			{
				"internalType": "bool",
				"name": "",
				"type": "bool"
			}
		],
		"stateMutability": "view",
		"type": "function"
	},
	{
		"inputs": [],
		"name": "roundNum",
		"outputs": [
			{
				"internalType": "uint256",
				"name": "",
				"type": "uint256"
			}
		],
		"stateMutability": "view",
		"type": "function"
	},
	{
		"inputs": [],
		"name": "roundStartTimeStamp",
		"outputs": [
			{
				"internalType": "uint256",
				"name": "",
				"type": "uint256"
			}
		],
		"stateMutability": "view",
		"type": "function"
	},
	{
		"inputs": [],
		"name": "roundTime",
		"outputs": [
			{
				"internalType": "uint256",
				"name": "",
				"type": "uint256"
			}
		],
		"stateMutability": "view",
		"type": "function"
	},
	{
		"inputs": [
			{
				"internalType": "uint256",
				"name": "",
				"type": "uint256"
			}
		],
		"name": "roundUpdateList",
		"outputs": [
			{
				"internalType": "bool",
				"name": "",
				"type": "bool"
			}
		],
		"stateMutability": "view",
		"type": "function"
	},
	{
		"inputs": [],
		"name": "updateCounter",
		"outputs": [
			{
				"internalType": "uint256",
				"name": "",
				"type": "uint256"
			}
		],
		"stateMutability": "view",
		"type": "function"
	}
]
